jupyterlab_bqn/__init__.py
jupyterlab_bqn/_version.py
jupyterlab_bqn-0.1.1.data/data/share/jupyter/labextensions/jupyterlab-bqn/package.json
jupyterlab_bqn-0.1.1.data/data/share/jupyter/labextensions/jupyterlab-bqn/static/34.93a1c5af2113cf0dee64.js
jupyterlab_bqn-0.1.1.data/data/share/jupyter/labextensions/jupyterlab-bqn/static/568.7a272e65f3b5590c7a38.js
jupyterlab_bqn-0.1.1.data/data/share/jupyter/labextensions/jupyterlab-bqn/static/747.3001e38079588c555ff0.js
jupyterlab_bqn-0.1.1.data/data/share/jupyter/labextensions/jupyterlab-bqn/static/remoteEntry.40326b1f39601233dc4c.js
jupyterlab_bqn-0.1.1.data/data/share/jupyter/labextensions/jupyterlab-bqn/static/style.js
jupyterlab_bqn-0.1.1.data/data/share/jupyter/labextensions/jupyterlab-bqn/static/third-party-licenses.json
jupyterlab_bqn-0.1.1.data/data/share/jupyter/labextensions/jupyterlab-bqn/install.json
jupyterlab_bqn-0.1.1.dist-info/METADATA
jupyterlab_bqn-0.1.1.dist-info/WHEEL
jupyterlab_bqn-0.1.1.dist-info/licenses/LICENSE
jupyterlab_bqn-0.1.1.dist-info/RECORD
